mkdocs_helm/__init__.py
mkdocs_helm/repository.py
mkdocs_helm-1.0.2.dist-info/LICENSE
mkdocs_helm-1.0.2.dist-info/METADATA
mkdocs_helm-1.0.2.dist-info/WHEEL
mkdocs_helm-1.0.2.dist-info/entry_points.txt
mkdocs_helm-1.0.2.dist-info/top_level.txt
mkdocs_helm-1.0.2.dist-info/RECORD
