Metadata-Version: 2.1
Name: mkdocs-helm
Version: 1.0.2
Summary: An mkdocs plugin for publishing helm repository
Home-page: https://github.com/M00nF1sh/mkdocs_helm
Author: M00nF1sh
Author-email: Me_Fortune@qq.com
License: UNKNOWN
Platform: UNKNOWN
Classifier: Programming Language :: Python :: 3
Classifier: License :: OSI Approved :: MIT License
Classifier: Operating System :: OS Independent
